growupmore_utils/__init__.py
growupmore_utils/db_utils.py
growupmore_utils/err_utils.py
growupmore_utils/user_utils.py
growupmore_utils-1.0.0.dist-info/METADATA
growupmore_utils-1.0.0.dist-info/WHEEL
growupmore_utils-1.0.0.dist-info/top_level.txt
growupmore_utils-1.0.0.dist-info/RECORD
