Metadata-Version: 2.1
Name: growupmore_utils
Version: 1.0.0
Summary: A utility package for common functionalities.
Home-page: https://github.com/girishinindia/test
Author: Girish Chaudhary
Author-email: girishinindia@gmail.com
License: MIT
Classifier: Framework :: Django
Classifier: Intended Audience :: Developers
Classifier: License :: OSI Approved :: MIT License
Classifier: Programming Language :: Python :: 3
Classifier: Programming Language :: Python :: 3.8
Requires-Dist: Django >=5.0.4
Requires-Dist: djangorestframework >=3.15.1
Requires-Dist: django-user-agents >=0.4.0
